Metadata-Version: 2.3
Name: django-plugin-tasks
Version: 0.1.1
Summary: Django plugin wrapping django_tasks for background work
Author: Joel Sleppy
Author-email: Joel Sleppy <joel@sleppytech.com>
License: Apache-2.0
Classifier: License :: OSI Approved :: Apache Software License
Requires-Dist: django
Requires-Dist: djp>=0.3.1
Requires-Dist: django-tasks==0.8.*
